odoo8_addon_l10n_it_withholding_tax-8.0.4.0.1-nspkg.pth
odoo_addons/l10n_it_withholding_tax/README.rst
odoo_addons/l10n_it_withholding_tax/__init__.py
odoo_addons/l10n_it_withholding_tax/__openerp__.py
odoo_addons/l10n_it_withholding_tax/workflow.xml
odoo_addons/l10n_it_withholding_tax/i18n/it.po
odoo_addons/l10n_it_withholding_tax/i18n/l10n_it_withholding_tax.pot
odoo_addons/l10n_it_withholding_tax/i18n/sl.po
odoo_addons/l10n_it_withholding_tax/models/__init__.py
odoo_addons/l10n_it_withholding_tax/models/account.py
odoo_addons/l10n_it_withholding_tax/models/product.py
odoo_addons/l10n_it_withholding_tax/models/voucher.py
odoo_addons/l10n_it_withholding_tax/models/withholding_tax.py
odoo_addons/l10n_it_withholding_tax/security/ir.model.access.csv
odoo_addons/l10n_it_withholding_tax/static/description/icon.png
odoo_addons/l10n_it_withholding_tax/tests/__init__.py
odoo_addons/l10n_it_withholding_tax/tests/test_invoice_multi_line_tax.py
odoo_addons/l10n_it_withholding_tax/views/account.xml
odoo_addons/l10n_it_withholding_tax/views/product.xml
odoo_addons/l10n_it_withholding_tax/views/voucher.xml
odoo_addons/l10n_it_withholding_tax/views/withholding_tax.xml
odoo_addons/l10n_it_withholding_tax/wizard/__init__.py
odoo_addons/l10n_it_withholding_tax/wizard/create_wt_statement.py
odoo_addons/l10n_it_withholding_tax/wizard/create_wt_statement_view.xml
odoo8_addon_l10n_it_withholding_tax-8.0.4.0.1.dist-info/METADATA
odoo8_addon_l10n_it_withholding_tax-8.0.4.0.1.dist-info/WHEEL
odoo8_addon_l10n_it_withholding_tax-8.0.4.0.1.dist-info/namespace_packages.txt
odoo8_addon_l10n_it_withholding_tax-8.0.4.0.1.dist-info/top_level.txt
odoo8_addon_l10n_it_withholding_tax-8.0.4.0.1.dist-info/RECORD
